[
  {
    "Vek": "0",
    "Počet_občanov_v_danom_veku": "   799",
    "Počet_mužov": "   422",
    "Počet_žien": "   377"
  },
  {
    "Vek": "1",
    "Počet_občanov_v_danom_veku": "   897",
    "Počet_mužov": "   454",
    "Počet_žien": "   443"
  },
  {
    "Vek": "2",
    "Počet_občanov_v_danom_veku": "   890",
    "Počet_mužov": "   477",
    "Počet_žien": "   413"
  },
  {
    "Vek": "3",
    "Počet_občanov_v_danom_veku": "   859",
    "Počet_mužov": "   441",
    "Počet_žien": "   418"
  },
  {
    "Vek": "4",
    "Počet_občanov_v_danom_veku": "   879",
    "Počet_mužov": "   456",
    "Počet_žien": "   423"
  },
  {
    "Vek": "5",
    "Počet_občanov_v_danom_veku": "   891",
    "Počet_mužov": "   489",
    "Počet_žien": "   402"
  },
  {
    "Vek": "6",
    "Počet_občanov_v_danom_veku": "   843",
    "Počet_mužov": "   436",
    "Počet_žien": "   407"
  },
  {
    "Vek": "7",
    "Počet_občanov_v_danom_veku": "   758",
    "Počet_mužov": "   398",
    "Počet_žien": "   360"
  },
  {
    "Vek": "8",
    "Počet_občanov_v_danom_veku": "   817",
    "Počet_mužov": "   435",
    "Počet_žien": "   382"
  },
  {
    "Vek": "9",
    "Počet_občanov_v_danom_veku": "   836",
    "Počet_mužov": "   443",
    "Počet_žien": "   393"
  },
  {
    "Vek": "10",
    "Počet_občanov_v_danom_veku": "   818",
    "Počet_mužov": "   439",
    "Počet_žien": "   379"
  },
  {
    "Vek": "11",
    "Počet_občanov_v_danom_veku": "   847",
    "Počet_mužov": "   436",
    "Počet_žien": "   411"
  },
  {
    "Vek": "12",
    "Počet_občanov_v_danom_veku": "   765",
    "Počet_mužov": "   388",
    "Počet_žien": "   377"
  },
  {
    "Vek": "13",
    "Počet_občanov_v_danom_veku": "   729",
    "Počet_mužov": "   378",
    "Počet_žien": "   351"
  },
  {
    "Vek": "14",
    "Počet_občanov_v_danom_veku": "   725",
    "Počet_mužov": "   385",
    "Počet_žien": "   340"
  },
  {
    "Vek": "15",
    "Počet_občanov_v_danom_veku": "   697",
    "Počet_mužov": "   358",
    "Počet_žien": "   339"
  },
  {
    "Vek": "16",
    "Počet_občanov_v_danom_veku": "   719",
    "Počet_mužov": "   374",
    "Počet_žien": "   345"
  },
  {
    "Vek": "17",
    "Počet_občanov_v_danom_veku": "   671",
    "Počet_mužov": "   336",
    "Počet_žien": "   335"
  },
  {
    "Vek": "18",
    "Počet_občanov_v_danom_veku": "   616",
    "Počet_mužov": "   316",
    "Počet_žien": "   300"
  },
  {
    "Vek": "19",
    "Počet_občanov_v_danom_veku": "   622",
    "Počet_mužov": "   320",
    "Počet_žien": "   302"
  },
  {
    "Vek": "20",
    "Počet_občanov_v_danom_veku": "   655",
    "Počet_mužov": "   325",
    "Počet_žien": "   330"
  },
  {
    "Vek": "21",
    "Počet_občanov_v_danom_veku": "   737",
    "Počet_mužov": "   384",
    "Počet_žien": "   353"
  },
  {
    "Vek": "22",
    "Počet_občanov_v_danom_veku": "   732",
    "Počet_mužov": "   390",
    "Počet_žien": "   342"
  },
  {
    "Vek": "23",
    "Počet_občanov_v_danom_veku": "   724",
    "Počet_mužov": "   374",
    "Počet_žien": "   350"
  },
  {
    "Vek": "24",
    "Počet_občanov_v_danom_veku": "   757",
    "Počet_mužov": "   401",
    "Počet_žien": "   356"
  },
  {
    "Vek": "25",
    "Počet_občanov_v_danom_veku": "   813",
    "Počet_mužov": "   424",
    "Počet_žien": "   389"
  },
  {
    "Vek": "26",
    "Počet_občanov_v_danom_veku": "   788",
    "Počet_mužov": "   407",
    "Počet_žien": "   381"
  },
  {
    "Vek": "27",
    "Počet_občanov_v_danom_veku": "  1 011",
    "Počet_mužov": "   500",
    "Počet_žien": "   511"
  },
  {
    "Vek": "28",
    "Počet_občanov_v_danom_veku": "  1 005",
    "Počet_mužov": "   495",
    "Počet_žien": "   510"
  },
  {
    "Vek": "29",
    "Počet_občanov_v_danom_veku": "  1 077",
    "Počet_mužov": "   555",
    "Počet_žien": "   522"
  },
  {
    "Vek": "30",
    "Počet_občanov_v_danom_veku": "  1 190",
    "Počet_mužov": "   602",
    "Počet_žien": "   588"
  },
  {
    "Vek": "31",
    "Počet_občanov_v_danom_veku": "  1 180",
    "Počet_mužov": "   580",
    "Počet_žien": "   600"
  },
  {
    "Vek": "32",
    "Počet_občanov_v_danom_veku": "  1 318",
    "Počet_mužov": "   677",
    "Počet_žien": "   641"
  },
  {
    "Vek": "33",
    "Počet_občanov_v_danom_veku": "  1 324",
    "Počet_mužov": "   671",
    "Počet_žien": "   653"
  },
  {
    "Vek": "34",
    "Počet_občanov_v_danom_veku": "  1 364",
    "Počet_mužov": "   700",
    "Počet_žien": "   664"
  },
  {
    "Vek": "35",
    "Počet_občanov_v_danom_veku": "  1 423",
    "Počet_mužov": "   726",
    "Počet_žien": "   697"
  },
  {
    "Vek": "36",
    "Počet_občanov_v_danom_veku": "  1 356",
    "Počet_mužov": "   724",
    "Počet_žien": "   632"
  },
  {
    "Vek": "37",
    "Počet_občanov_v_danom_veku": "  1 455",
    "Počet_mužov": "   742",
    "Počet_žien": "   713"
  },
  {
    "Vek": "38",
    "Počet_občanov_v_danom_veku": "  1 401",
    "Počet_mužov": "   730",
    "Počet_žien": "   671"
  },
  {
    "Vek": "39",
    "Počet_občanov_v_danom_veku": "  1 357",
    "Počet_mužov": "   708",
    "Počet_žien": "   649"
  },
  {
    "Vek": "40",
    "Počet_občanov_v_danom_veku": "  1 359",
    "Počet_mužov": "   690",
    "Počet_žien": "   669"
  },
  {
    "Vek": "41",
    "Počet_občanov_v_danom_veku": "  1 494",
    "Počet_mužov": "   771",
    "Počet_žien": "   723"
  },
  {
    "Vek": "42",
    "Počet_občanov_v_danom_veku": "  1 509",
    "Počet_mužov": "   750",
    "Počet_žien": "   759"
  },
  {
    "Vek": "43",
    "Počet_občanov_v_danom_veku": "  1 447",
    "Počet_mužov": "   729",
    "Počet_žien": "   718"
  },
  {
    "Vek": "44",
    "Počet_občanov_v_danom_veku": "  1 422",
    "Počet_mužov": "   743",
    "Počet_žien": "   679"
  },
  {
    "Vek": "45",
    "Počet_občanov_v_danom_veku": "  1 299",
    "Počet_mužov": "   657",
    "Počet_žien": "   642"
  },
  {
    "Vek": "46",
    "Počet_občanov_v_danom_veku": "  1 286",
    "Počet_mužov": "   697",
    "Počet_žien": "   589"
  },
  {
    "Vek": "47",
    "Počet_občanov_v_danom_veku": "  1 179",
    "Počet_mužov": "   569",
    "Počet_žien": "   610"
  },
  {
    "Vek": "48",
    "Počet_občanov_v_danom_veku": "  1 155",
    "Počet_mužov": "   577",
    "Počet_žien": "   578"
  },
  {
    "Vek": "49",
    "Počet_občanov_v_danom_veku": "  1 089",
    "Počet_mužov": "   544",
    "Počet_žien": "   545"
  },
  {
    "Vek": "50",
    "Počet_občanov_v_danom_veku": "  1 006",
    "Počet_mužov": "   471",
    "Počet_žien": "   535"
  },
  {
    "Vek": "51",
    "Počet_občanov_v_danom_veku": "  1 000",
    "Počet_mužov": "   479",
    "Počet_žien": "   521"
  },
  {
    "Vek": "52",
    "Počet_občanov_v_danom_veku": "   933",
    "Počet_mužov": "   438",
    "Počet_žien": "   495"
  },
  {
    "Vek": "53",
    "Počet_občanov_v_danom_veku": "   927",
    "Počet_mužov": "   441",
    "Počet_žien": "   486"
  },
  {
    "Vek": "54",
    "Počet_občanov_v_danom_veku": "   977",
    "Počet_mužov": "   430",
    "Počet_žien": "   547"
  },
  {
    "Vek": "55",
    "Počet_občanov_v_danom_veku": "  1 022",
    "Počet_mužov": "   484",
    "Počet_žien": "   538"
  },
  {
    "Vek": "56",
    "Počet_občanov_v_danom_veku": "  1 133",
    "Počet_mužov": "   520",
    "Počet_žien": "   613"
  },
  {
    "Vek": "57",
    "Počet_občanov_v_danom_veku": "  1 134",
    "Počet_mužov": "   533",
    "Počet_žien": "   601"
  },
  {
    "Vek": "58",
    "Počet_občanov_v_danom_veku": "  1 078",
    "Počet_mužov": "   502",
    "Počet_žien": "   576"
  },
  {
    "Vek": "59",
    "Počet_občanov_v_danom_veku": "  1 156",
    "Počet_mužov": "   524",
    "Počet_žien": "   632"
  },
  {
    "Vek": "60",
    "Počet_občanov_v_danom_veku": "  1 130",
    "Počet_mužov": "   531",
    "Počet_žien": "   599"
  },
  {
    "Vek": "61",
    "Počet_občanov_v_danom_veku": "  1 141",
    "Počet_mužov": "   531",
    "Počet_žien": "   610"
  },
  {
    "Vek": "62",
    "Počet_občanov_v_danom_veku": "  1 075",
    "Počet_mužov": "   477",
    "Počet_žien": "   598"
  },
  {
    "Vek": "63",
    "Počet_občanov_v_danom_veku": "  1 182",
    "Počet_mužov": "   551",
    "Počet_žien": "   631"
  },
  {
    "Vek": "64",
    "Počet_občanov_v_danom_veku": "  1 250",
    "Počet_mužov": "   577",
    "Počet_žien": "   673"
  },
  {
    "Vek": "65",
    "Počet_občanov_v_danom_veku": "  1 234",
    "Počet_mužov": "   555",
    "Počet_žien": "   679"
  },
  {
    "Vek": "66",
    "Počet_občanov_v_danom_veku": "  1 154",
    "Počet_mužov": "   496",
    "Počet_žien": "   658"
  },
  {
    "Vek": "67",
    "Počet_občanov_v_danom_veku": "  1 107",
    "Počet_mužov": "   487",
    "Počet_žien": "   620"
  },
  {
    "Vek": "68",
    "Počet_občanov_v_danom_veku": "  1 013",
    "Počet_mužov": "   441",
    "Počet_žien": "   572"
  },
  {
    "Vek": "69",
    "Počet_občanov_v_danom_veku": "  1 071",
    "Počet_mužov": "   476",
    "Počet_žien": "   595"
  },
  {
    "Vek": "70",
    "Počet_občanov_v_danom_veku": "   965",
    "Počet_mužov": "   431",
    "Počet_žien": "   534"
  },
  {
    "Vek": "71",
    "Počet_občanov_v_danom_veku": "   898",
    "Počet_mužov": "   381",
    "Počet_žien": "   517"
  },
  {
    "Vek": "72",
    "Počet_občanov_v_danom_veku": "   830",
    "Počet_mužov": "   374",
    "Počet_žien": "   456"
  },
  {
    "Vek": "73",
    "Počet_občanov_v_danom_veku": "   839",
    "Počet_mužov": "   334",
    "Počet_žien": "   505"
  },
  {
    "Vek": "74",
    "Počet_občanov_v_danom_veku": "   711",
    "Počet_mužov": "   279",
    "Počet_žien": "   432"
  },
  {
    "Vek": "75",
    "Počet_občanov_v_danom_veku": "   605",
    "Počet_mužov": "   248",
    "Počet_žien": "   357"
  },
  {
    "Vek": "76",
    "Počet_občanov_v_danom_veku": "   542",
    "Počet_mužov": "   195",
    "Počet_žien": "   347"
  },
  {
    "Vek": "77",
    "Počet_občanov_v_danom_veku": "   468",
    "Počet_mužov": "   178",
    "Počet_žien": "   290"
  },
  {
    "Vek": "78",
    "Počet_občanov_v_danom_veku": "   496",
    "Počet_mužov": "   187",
    "Počet_žien": "   309"
  },
  {
    "Vek": "79",
    "Počet_občanov_v_danom_veku": "   450",
    "Počet_mužov": "   165",
    "Počet_žien": "   285"
  },
  {
    "Vek": "80",
    "Počet_občanov_v_danom_veku": "   405",
    "Počet_mužov": "   146",
    "Počet_žien": "   259"
  },
  {
    "Vek": "81",
    "Počet_občanov_v_danom_veku": "   389",
    "Počet_mužov": "   150",
    "Počet_žien": "   239"
  },
  {
    "Vek": "82",
    "Počet_občanov_v_danom_veku": "   310",
    "Počet_mužov": "   97",
    "Počet_žien": "   213"
  },
  {
    "Vek": "83",
    "Počet_občanov_v_danom_veku": "   263",
    "Počet_mužov": "   77",
    "Počet_žien": "   186"
  },
  {
    "Vek": "84",
    "Počet_občanov_v_danom_veku": "   229",
    "Počet_mužov": "   71",
    "Počet_žien": "   158"
  },
  {
    "Vek": "85",
    "Počet_občanov_v_danom_veku": "   229",
    "Počet_mužov": "   65",
    "Počet_žien": "   164"
  },
  {
    "Vek": "86",
    "Počet_občanov_v_danom_veku": "   226",
    "Počet_mužov": "   59",
    "Počet_žien": "   167"
  },
  {
    "Vek": "87",
    "Počet_občanov_v_danom_veku": "   164",
    "Počet_mužov": "   49",
    "Počet_žien": "   115"
  },
  {
    "Vek": "88",
    "Počet_občanov_v_danom_veku": "   151",
    "Počet_mužov": "   36",
    "Počet_žien": "   115"
  },
  {
    "Vek": "89",
    "Počet_občanov_v_danom_veku": "   143",
    "Počet_mužov": "   35",
    "Počet_žien": "   108"
  },
  {
    "Vek": "90",
    "Počet_občanov_v_danom_veku": "   97",
    "Počet_mužov": "   30",
    "Počet_žien": "   67"
  },
  {
    "Vek": "91",
    "Počet_občanov_v_danom_veku": "   67",
    "Počet_mužov": "   21",
    "Počet_žien": "   46"
  },
  {
    "Vek": "92",
    "Počet_občanov_v_danom_veku": "   75",
    "Počet_mužov": "   17",
    "Počet_žien": "   58"
  },
  {
    "Vek": "93",
    "Počet_občanov_v_danom_veku": "   53",
    "Počet_mužov": "   15",
    "Počet_žien": "   38"
  },
  {
    "Vek": "94",
    "Počet_občanov_v_danom_veku": "   42",
    "Počet_mužov": "   9",
    "Počet_žien": "   33"
  },
  {
    "Vek": "95",
    "Počet_občanov_v_danom_veku": "   23",
    "Počet_mužov": "   4",
    "Počet_žien": "   19"
  },
  {
    "Vek": "96",
    "Počet_občanov_v_danom_veku": "   24",
    "Počet_mužov": "   9",
    "Počet_žien": "   15"
  },
  {
    "Vek": "97",
    "Počet_občanov_v_danom_veku": "   12",
    "Počet_mužov": "   3",
    "Počet_žien": "   9"
  },
  {
    "Vek": "98",
    "Počet_občanov_v_danom_veku": "   7",
    "Počet_mužov": "   2",
    "Počet_žien": "   5"
  },
  {
    "Vek": "99",
    "Počet_občanov_v_danom_veku": "   6",
    "Počet_mužov": "   1",
    "Počet_žien": "   5"
  },
  {
    "Vek": "100",
    "Počet_občanov_v_danom_veku": "   3",
    "Počet_mužov": "   0",
    "Počet_žien": "   3"
  },
  {
    "Vek": "101",
    "Počet_občanov_v_danom_veku": "   3",
    "Počet_mužov": "   1",
    "Počet_žien": "   2"
  },
  {
    "Vek": "102",
    "Počet_občanov_v_danom_veku": "   0",
    "Počet_mužov": "   0",
    "Počet_žien": "   0"
  },
  {
    "Vek": "103",
    "Počet_občanov_v_danom_veku": "   1",
    "Počet_mužov": "   1",
    "Počet_žien": "   0"
  },
  {
    "Vek": "104",
    "Počet_občanov_v_danom_veku": "   0",
    "Počet_mužov": "   0",
    "Počet_žien": "   0"
  },
  {
    "Vek": "105",
    "Počet_občanov_v_danom_veku": "   1",
    "Počet_mužov": "   1",
    "Počet_žien": "   0"
  },
  {
    "Vek": "106",
    "Počet_občanov_v_danom_veku": "   0",
    "Počet_mužov": "   0",
    "Počet_žien": "   0"
  },
  {
    "Vek": "107",
    "Počet_občanov_v_danom_veku": "   1",
    "Počet_mužov": "   0",
    "Počet_žien": "   1"
  },
  {
    "Vek": "108",
    "Počet_občanov_v_danom_veku": "   1",
    "Počet_mužov": "   0",
    "Počet_žien": "   1"
  },
  {
    "Vek": "109",
    "Počet_občanov_v_danom_veku": "   0",
    "Počet_mužov": "   0",
    "Počet_žien": "   0"
  },
  {
    "Vek": "110",
    "Počet_občanov_v_danom_veku": "   0",
    "Počet_mužov": "   0",
    "Počet_žien": "   0"
  },
  {
    "Vek": "111",
    "Počet_občanov_v_danom_veku": "   0",
    "Počet_mužov": "   0",
    "Počet_žien": "   0"
  },
  {
    "Vek": "112",
    "Počet_občanov_v_danom_veku": "   0",
    "Počet_mužov": "   0",
    "Počet_žien": "   0"
  },
  {
    "Vek": "113",
    "Počet_občanov_v_danom_veku": "   0",
    "Počet_mužov": "   0",
    "Počet_žien": "   0"
  },
  {
    "Vek": "114",
    "Počet_občanov_v_danom_veku": "   0",
    "Počet_mužov": "   0",
    "Počet_žien": "   0"
  },
  {
    "Vek": "115",
    "Počet_občanov_v_danom_veku": "   0",
    "Počet_mužov": "   0",
    "Počet_žien": "   0"
  },
  {
    "Vek": "116",
    "Počet_občanov_v_danom_veku": "   0",
    "Počet_mužov": "   0",
    "Počet_žien": "   0"
  },
  {
    "Vek": "117",
    "Počet_občanov_v_danom_veku": "   0",
    "Počet_mužov": "   0",
    "Počet_žien": "   0"
  },
  {
    "Vek": "118",
    "Počet_občanov_v_danom_veku": "   0",
    "Počet_mužov": "   0",
    "Počet_žien": "   0"
  },
  {
    "Vek": "119",
    "Počet_občanov_v_danom_veku": "   0",
    "Počet_mužov": "   0",
    "Počet_žien": "   0"
  },
  {
    "Vek": "120",
    "Počet_občanov_v_danom_veku": "   0",
    "Počet_mužov": "   0",
    "Počet_žien": "   0"
  },
  {
    "Vek": "121",
    "Počet_občanov_v_danom_veku": "   0",
    "Počet_mužov": "   0",
    "Počet_žien": "   0"
  },
  {
    "Vek": "122",
    "Počet_občanov_v_danom_veku": "   0",
    "Počet_mužov": "   0",
    "Počet_žien": "   0"
  },
  {
    "Vek": "123",
    "Počet_občanov_v_danom_veku": "   0",
    "Počet_mužov": "   0",
    "Počet_žien": "   0"
  },
  {
    "Vek": "124",
    "Počet_občanov_v_danom_veku": "   0",
    "Počet_mužov": "   0",
    "Počet_žien": "   0"
  },
  {
    "Vek": "125",
    "Počet_občanov_v_danom_veku": "   0",
    "Počet_mužov": "   0",
    "Počet_žien": "   0"
  },
  {
    "Vek": "126",
    "Počet_občanov_v_danom_veku": "   0",
    "Počet_mužov": "   0",
    "Počet_žien": "   0"
  },
  {
    "Vek": "127",
    "Počet_občanov_v_danom_veku": "   0",
    "Počet_mužov": "   0",
    "Počet_žien": "   0"
  }
]