[
  {
    "Vek": "0",
    "Počet_občanov_v_danom_veku": "   790",
    "Počet_mužov": "   385",
    "Počet_žien": "   405"
  },
  {
    "Vek": "1",
    "Počet_občanov_v_danom_veku": "   847",
    "Počet_mužov": "   455",
    "Počet_žien": "   392"
  },
  {
    "Vek": "2",
    "Počet_občanov_v_danom_veku": "   900",
    "Počet_mužov": "   450",
    "Počet_žien": "   450"
  },
  {
    "Vek": "3",
    "Počet_občanov_v_danom_veku": "   875",
    "Počet_mužov": "   465",
    "Počet_žien": "   410"
  },
  {
    "Vek": "4",
    "Počet_občanov_v_danom_veku": "   870",
    "Počet_mužov": "   442",
    "Počet_žien": "   428"
  },
  {
    "Vek": "5",
    "Počet_občanov_v_danom_veku": "   842",
    "Počet_mužov": "   437",
    "Počet_žien": "   405"
  },
  {
    "Vek": "6",
    "Počet_občanov_v_danom_veku": "   885",
    "Počet_mužov": "   476",
    "Počet_žien": "   409"
  },
  {
    "Vek": "7",
    "Počet_občanov_v_danom_veku": "   812",
    "Počet_mužov": "   430",
    "Počet_žien": "   382"
  },
  {
    "Vek": "8",
    "Počet_občanov_v_danom_veku": "   750",
    "Počet_mužov": "   395",
    "Počet_žien": "   355"
  },
  {
    "Vek": "9",
    "Počet_občanov_v_danom_veku": "   825",
    "Počet_mužov": "   436",
    "Počet_žien": "   389"
  },
  {
    "Vek": "10",
    "Počet_občanov_v_danom_veku": "   825",
    "Počet_mužov": "   444",
    "Počet_žien": "   381"
  },
  {
    "Vek": "11",
    "Počet_občanov_v_danom_veku": "   815",
    "Počet_mužov": "   439",
    "Počet_žien": "   376"
  },
  {
    "Vek": "12",
    "Počet_občanov_v_danom_veku": "   818",
    "Počet_mužov": "   403",
    "Počet_žien": "   415"
  },
  {
    "Vek": "13",
    "Počet_občanov_v_danom_veku": "   747",
    "Počet_mužov": "   369",
    "Počet_žien": "   378"
  },
  {
    "Vek": "14",
    "Počet_občanov_v_danom_veku": "   753",
    "Počet_mužov": "   399",
    "Počet_žien": "   354"
  },
  {
    "Vek": "15",
    "Počet_občanov_v_danom_veku": "   670",
    "Počet_mužov": "   366",
    "Počet_žien": "   304"
  },
  {
    "Vek": "16",
    "Počet_občanov_v_danom_veku": "   726",
    "Počet_mužov": "   375",
    "Počet_žien": "   351"
  },
  {
    "Vek": "17",
    "Počet_občanov_v_danom_veku": "   705",
    "Počet_mužov": "   360",
    "Počet_žien": "   345"
  },
  {
    "Vek": "18",
    "Počet_občanov_v_danom_veku": "   649",
    "Počet_mužov": "   322",
    "Počet_žien": "   327"
  },
  {
    "Vek": "19",
    "Počet_občanov_v_danom_veku": "   624",
    "Počet_mužov": "   321",
    "Počet_žien": "   303"
  },
  {
    "Vek": "20",
    "Počet_občanov_v_danom_veku": "   634",
    "Počet_mužov": "   327",
    "Počet_žien": "   307"
  },
  {
    "Vek": "21",
    "Počet_občanov_v_danom_veku": "   679",
    "Počet_mužov": "   347",
    "Počet_žien": "   332"
  },
  {
    "Vek": "22",
    "Počet_občanov_v_danom_veku": "   719",
    "Počet_mužov": "   371",
    "Počet_žien": "   348"
  },
  {
    "Vek": "23",
    "Počet_občanov_v_danom_veku": "   745",
    "Počet_mužov": "   395",
    "Počet_žien": "   350"
  },
  {
    "Vek": "24",
    "Počet_občanov_v_danom_veku": "   748",
    "Počet_mužov": "   383",
    "Počet_žien": "   365"
  },
  {
    "Vek": "25",
    "Počet_občanov_v_danom_veku": "   748",
    "Počet_mužov": "   399",
    "Počet_žien": "   349"
  },
  {
    "Vek": "26",
    "Počet_občanov_v_danom_veku": "   819",
    "Počet_mužov": "   417",
    "Počet_žien": "   402"
  },
  {
    "Vek": "27",
    "Počet_občanov_v_danom_veku": "   858",
    "Počet_mužov": "   465",
    "Počet_žien": "   393"
  },
  {
    "Vek": "28",
    "Počet_občanov_v_danom_veku": "  1 031",
    "Počet_mužov": "   502",
    "Počet_žien": "   529"
  },
  {
    "Vek": "29",
    "Počet_občanov_v_danom_veku": "  1 032",
    "Počet_mužov": "   505",
    "Počet_žien": "   527"
  },
  {
    "Vek": "30",
    "Počet_občanov_v_danom_veku": "  1 095",
    "Počet_mužov": "   560",
    "Počet_žien": "   535"
  },
  {
    "Vek": "31",
    "Počet_občanov_v_danom_veku": "  1 214",
    "Počet_mužov": "   619",
    "Počet_žien": "   595"
  },
  {
    "Vek": "32",
    "Počet_občanov_v_danom_veku": "  1 225",
    "Počet_mužov": "   593",
    "Počet_žien": "   632"
  },
  {
    "Vek": "33",
    "Počet_občanov_v_danom_veku": "  1 317",
    "Počet_mužov": "   685",
    "Počet_žien": "   632"
  },
  {
    "Vek": "34",
    "Počet_občanov_v_danom_veku": "  1 317",
    "Počet_mužov": "   668",
    "Počet_žien": "   649"
  },
  {
    "Vek": "35",
    "Počet_občanov_v_danom_veku": "  1 349",
    "Počet_mužov": "   691",
    "Počet_žien": "   658"
  },
  {
    "Vek": "36",
    "Počet_občanov_v_danom_veku": "  1 411",
    "Počet_mužov": "   711",
    "Počet_žien": "   700"
  },
  {
    "Vek": "37",
    "Počet_občanov_v_danom_veku": "  1 366",
    "Počet_mužov": "   723",
    "Počet_žien": "   643"
  },
  {
    "Vek": "38",
    "Počet_občanov_v_danom_veku": "  1 453",
    "Počet_mužov": "   767",
    "Počet_žien": "   686"
  },
  {
    "Vek": "39",
    "Počet_občanov_v_danom_veku": "  1 319",
    "Počet_mužov": "   691",
    "Počet_žien": "   628"
  },
  {
    "Vek": "40",
    "Počet_občanov_v_danom_veku": "  1 399",
    "Počet_mužov": "   710",
    "Počet_žien": "   689"
  },
  {
    "Vek": "41",
    "Počet_občanov_v_danom_veku": "  1 373",
    "Počet_mužov": "   711",
    "Počet_žien": "   662"
  },
  {
    "Vek": "42",
    "Počet_občanov_v_danom_veku": "  1 516",
    "Počet_mužov": "   773",
    "Počet_žien": "   743"
  },
  {
    "Vek": "43",
    "Počet_občanov_v_danom_veku": "  1 459",
    "Počet_mužov": "   740",
    "Počet_žien": "   719"
  },
  {
    "Vek": "44",
    "Počet_občanov_v_danom_veku": "  1 413",
    "Počet_mužov": "   710",
    "Počet_žien": "   703"
  },
  {
    "Vek": "45",
    "Počet_občanov_v_danom_veku": "  1 411",
    "Počet_mužov": "   739",
    "Počet_žien": "   672"
  },
  {
    "Vek": "46",
    "Počet_občanov_v_danom_veku": "  1 321",
    "Počet_mužov": "   679",
    "Počet_žien": "   642"
  },
  {
    "Vek": "47",
    "Počet_občanov_v_danom_veku": "  1 208",
    "Počet_mužov": "   610",
    "Počet_žien": "   598"
  },
  {
    "Vek": "48",
    "Počet_občanov_v_danom_veku": "  1 131",
    "Počet_mužov": "   566",
    "Počet_žien": "   565"
  },
  {
    "Vek": "49",
    "Počet_občanov_v_danom_veku": "  1 140",
    "Počet_mužov": "   570",
    "Počet_žien": "   570"
  },
  {
    "Vek": "50",
    "Počet_občanov_v_danom_veku": "  1 057",
    "Počet_mužov": "   512",
    "Počet_žien": "   545"
  },
  {
    "Vek": "51",
    "Počet_občanov_v_danom_veku": "  1 000",
    "Počet_mužov": "   484",
    "Počet_žien": "   516"
  },
  {
    "Vek": "52",
    "Počet_občanov_v_danom_veku": "   975",
    "Počet_mužov": "   432",
    "Počet_žien": "   543"
  },
  {
    "Vek": "53",
    "Počet_občanov_v_danom_veku": "   942",
    "Počet_mužov": "   463",
    "Počet_žien": "   479"
  },
  {
    "Vek": "54",
    "Počet_občanov_v_danom_veku": "   897",
    "Počet_mužov": "   407",
    "Počet_žien": "   490"
  },
  {
    "Vek": "55",
    "Počet_občanov_v_danom_veku": "   960",
    "Počet_mužov": "   427",
    "Počet_žien": "   533"
  },
  {
    "Vek": "56",
    "Počet_občanov_v_danom_veku": "  1 072",
    "Počet_mužov": "   510",
    "Počet_žien": "   562"
  },
  {
    "Vek": "57",
    "Počet_občanov_v_danom_veku": "  1 131",
    "Počet_mužov": "   531",
    "Počet_žien": "   600"
  },
  {
    "Vek": "58",
    "Počet_občanov_v_danom_veku": "  1 143",
    "Počet_mužov": "   527",
    "Počet_žien": "   616"
  },
  {
    "Vek": "59",
    "Počet_občanov_v_danom_veku": "  1 057",
    "Počet_mužov": "   496",
    "Počet_žien": "   561"
  },
  {
    "Vek": "60",
    "Počet_občanov_v_danom_veku": "  1 153",
    "Počet_mužov": "   518",
    "Počet_žien": "   635"
  },
  {
    "Vek": "61",
    "Počet_občanov_v_danom_veku": "  1 108",
    "Počet_mužov": "   498",
    "Počet_žien": "   610"
  },
  {
    "Vek": "62",
    "Počet_občanov_v_danom_veku": "  1 076",
    "Počet_mužov": "   508",
    "Počet_žien": "   568"
  },
  {
    "Vek": "63",
    "Počet_občanov_v_danom_veku": "  1 138",
    "Počet_mužov": "   508",
    "Počet_žien": "   630"
  },
  {
    "Vek": "64",
    "Počet_občanov_v_danom_veku": "  1 154",
    "Počet_mužov": "   537",
    "Počet_žien": "   617"
  },
  {
    "Vek": "65",
    "Počet_občanov_v_danom_veku": "  1 268",
    "Počet_mužov": "   568",
    "Počet_žien": "   700"
  },
  {
    "Vek": "66",
    "Počet_občanov_v_danom_veku": "  1 192",
    "Počet_mužov": "   546",
    "Počet_žien": "   646"
  },
  {
    "Vek": "67",
    "Počet_občanov_v_danom_veku": "  1 091",
    "Počet_mužov": "   467",
    "Počet_žien": "   624"
  },
  {
    "Vek": "68",
    "Počet_občanov_v_danom_veku": "  1 103",
    "Počet_mužov": "   458",
    "Počet_žien": "   645"
  },
  {
    "Vek": "69",
    "Počet_občanov_v_danom_veku": "  1 012",
    "Počet_mužov": "   459",
    "Počet_žien": "   553"
  },
  {
    "Vek": "70",
    "Počet_občanov_v_danom_veku": "  1 024",
    "Počet_mužov": "   454",
    "Počet_žien": "   570"
  },
  {
    "Vek": "71",
    "Počet_občanov_v_danom_veku": "   912",
    "Počet_mužov": "   391",
    "Počet_žien": "   521"
  },
  {
    "Vek": "72",
    "Počet_občanov_v_danom_veku": "   849",
    "Počet_mužov": "   366",
    "Počet_žien": "   483"
  },
  {
    "Vek": "73",
    "Počet_občanov_v_danom_veku": "   833",
    "Počet_mužov": "   344",
    "Počet_žien": "   489"
  },
  {
    "Vek": "74",
    "Počet_občanov_v_danom_veku": "   772",
    "Počet_mužov": "   301",
    "Počet_žien": "   471"
  },
  {
    "Vek": "75",
    "Počet_občanov_v_danom_veku": "   668",
    "Počet_mužov": "   275",
    "Počet_žien": "   393"
  },
  {
    "Vek": "76",
    "Počet_občanov_v_danom_veku": "   559",
    "Počet_mužov": "   214",
    "Počet_žien": "   345"
  },
  {
    "Vek": "77",
    "Počet_občanov_v_danom_veku": "   490",
    "Počet_mužov": "   175",
    "Počet_žien": "   315"
  },
  {
    "Vek": "78",
    "Počet_občanov_v_danom_veku": "   481",
    "Počet_mužov": "   183",
    "Počet_žien": "   298"
  },
  {
    "Vek": "79",
    "Počet_občanov_v_danom_veku": "   442",
    "Počet_mužov": "   165",
    "Počet_žien": "   277"
  },
  {
    "Vek": "80",
    "Počet_občanov_v_danom_veku": "   424",
    "Počet_mužov": "   145",
    "Počet_žien": "   279"
  },
  {
    "Vek": "81",
    "Počet_občanov_v_danom_veku": "   383",
    "Počet_mužov": "   139",
    "Počet_žien": "   244"
  },
  {
    "Vek": "82",
    "Počet_občanov_v_danom_veku": "   321",
    "Počet_mužov": "   115",
    "Počet_žien": "   206"
  },
  {
    "Vek": "83",
    "Počet_občanov_v_danom_veku": "   278",
    "Počet_mužov": "   85",
    "Počet_žien": "   193"
  },
  {
    "Vek": "84",
    "Počet_občanov_v_danom_veku": "   236",
    "Počet_mužov": "   58",
    "Počet_žien": "   178"
  },
  {
    "Vek": "85",
    "Počet_občanov_v_danom_veku": "   177",
    "Počet_mužov": "   62",
    "Počet_žien": "   115"
  },
  {
    "Vek": "86",
    "Počet_občanov_v_danom_veku": "   227",
    "Počet_mužov": "   59",
    "Počet_žien": "   168"
  },
  {
    "Vek": "87",
    "Počet_občanov_v_danom_veku": "   198",
    "Počet_mužov": "   53",
    "Počet_žien": "   145"
  },
  {
    "Vek": "88",
    "Počet_občanov_v_danom_veku": "   132",
    "Počet_mužov": "   36",
    "Počet_žien": "   96"
  },
  {
    "Vek": "89",
    "Počet_občanov_v_danom_veku": "   142",
    "Počet_mužov": "   33",
    "Počet_žien": "   109"
  },
  {
    "Vek": "90",
    "Počet_občanov_v_danom_veku": "   97",
    "Počet_mužov": "   27",
    "Počet_žien": "   70"
  },
  {
    "Vek": "91",
    "Počet_občanov_v_danom_veku": "   74",
    "Počet_mužov": "   24",
    "Počet_žien": "   50"
  },
  {
    "Vek": "92",
    "Počet_občanov_v_danom_veku": "   65",
    "Počet_mužov": "   14",
    "Počet_žien": "   51"
  },
  {
    "Vek": "93",
    "Počet_občanov_v_danom_veku": "   41",
    "Počet_mužov": "   16",
    "Počet_žien": "   25"
  },
  {
    "Vek": "94",
    "Počet_občanov_v_danom_veku": "   39",
    "Počet_mužov": "   8",
    "Počet_žien": "   31"
  },
  {
    "Vek": "95",
    "Počet_občanov_v_danom_veku": "   33",
    "Počet_mužov": "   7",
    "Počet_žien": "   26"
  },
  {
    "Vek": "96",
    "Počet_občanov_v_danom_veku": "   15",
    "Počet_mužov": "   3",
    "Počet_žien": "   12"
  },
  {
    "Vek": "97",
    "Počet_občanov_v_danom_veku": "   13",
    "Počet_mužov": "   4",
    "Počet_žien": "   9"
  },
  {
    "Vek": "98",
    "Počet_občanov_v_danom_veku": "   8",
    "Počet_mužov": "   3",
    "Počet_žien": "   5"
  },
  {
    "Vek": "99",
    "Počet_občanov_v_danom_veku": "   6",
    "Počet_mužov": "   1",
    "Počet_žien": "   5"
  },
  {
    "Vek": "100",
    "Počet_občanov_v_danom_veku": "   2",
    "Počet_mužov": "   0",
    "Počet_žien": "   2"
  },
  {
    "Vek": "101",
    "Počet_občanov_v_danom_veku": "   2",
    "Počet_mužov": "   0",
    "Počet_žien": "   2"
  },
  {
    "Vek": "102",
    "Počet_občanov_v_danom_veku": "   3",
    "Počet_mužov": "   1",
    "Počet_žien": "   2"
  },
  {
    "Vek": "103",
    "Počet_občanov_v_danom_veku": "   0",
    "Počet_mužov": "   0",
    "Počet_žien": "   0"
  },
  {
    "Vek": "104",
    "Počet_občanov_v_danom_veku": "   1",
    "Počet_mužov": "   1",
    "Počet_žien": "   0"
  },
  {
    "Vek": "105",
    "Počet_občanov_v_danom_veku": "   1",
    "Počet_mužov": "   1",
    "Počet_žien": "   0"
  },
  {
    "Vek": "106",
    "Počet_občanov_v_danom_veku": "   0",
    "Počet_mužov": "   0",
    "Počet_žien": "   0"
  },
  {
    "Vek": "107",
    "Počet_občanov_v_danom_veku": "   0",
    "Počet_mužov": "   0",
    "Počet_žien": "   0"
  },
  {
    "Vek": "108",
    "Počet_občanov_v_danom_veku": "   1",
    "Počet_mužov": "   0",
    "Počet_žien": "   1"
  },
  {
    "Vek": "109",
    "Počet_občanov_v_danom_veku": "   1",
    "Počet_mužov": "   0",
    "Počet_žien": "   1"
  },
  {
    "Vek": "110",
    "Počet_občanov_v_danom_veku": "   0",
    "Počet_mužov": "   0",
    "Počet_žien": "   0"
  },
  {
    "Vek": "111",
    "Počet_občanov_v_danom_veku": "   0",
    "Počet_mužov": "   0",
    "Počet_žien": "   0"
  },
  {
    "Vek": "112",
    "Počet_občanov_v_danom_veku": "   0",
    "Počet_mužov": "   0",
    "Počet_žien": "   0"
  },
  {
    "Vek": "113",
    "Počet_občanov_v_danom_veku": "   0",
    "Počet_mužov": "   0",
    "Počet_žien": "   0"
  },
  {
    "Vek": "114",
    "Počet_občanov_v_danom_veku": "   0",
    "Počet_mužov": "   0",
    "Počet_žien": "   0"
  },
  {
    "Vek": "115",
    "Počet_občanov_v_danom_veku": "   0",
    "Počet_mužov": "   0",
    "Počet_žien": "   0"
  },
  {
    "Vek": "116",
    "Počet_občanov_v_danom_veku": "   0",
    "Počet_mužov": "   0",
    "Počet_žien": "   0"
  },
  {
    "Vek": "117",
    "Počet_občanov_v_danom_veku": "   0",
    "Počet_mužov": "   0",
    "Počet_žien": "   0"
  },
  {
    "Vek": "118",
    "Počet_občanov_v_danom_veku": "   0",
    "Počet_mužov": "   0",
    "Počet_žien": "   0"
  },
  {
    "Vek": "119",
    "Počet_občanov_v_danom_veku": "   0",
    "Počet_mužov": "   0",
    "Počet_žien": "   0"
  },
  {
    "Vek": "120",
    "Počet_občanov_v_danom_veku": "   0",
    "Počet_mužov": "   0",
    "Počet_žien": "   0"
  },
  {
    "Vek": "121",
    "Počet_občanov_v_danom_veku": "   0",
    "Počet_mužov": "   0",
    "Počet_žien": "   0"
  },
  {
    "Vek": "122",
    "Počet_občanov_v_danom_veku": "   0",
    "Počet_mužov": "   0",
    "Počet_žien": "   0"
  },
  {
    "Vek": "123",
    "Počet_občanov_v_danom_veku": "   0",
    "Počet_mužov": "   0",
    "Počet_žien": "   0"
  },
  {
    "Vek": "124",
    "Počet_občanov_v_danom_veku": "   0",
    "Počet_mužov": "   0",
    "Počet_žien": "   0"
  },
  {
    "Vek": "125",
    "Počet_občanov_v_danom_veku": "   0",
    "Počet_mužov": "   0",
    "Počet_žien": "   0"
  },
  {
    "Vek": "126",
    "Počet_občanov_v_danom_veku": "   0",
    "Počet_mužov": "   0",
    "Počet_žien": "   0"
  },
  {
    "Vek": "127",
    "Počet_občanov_v_danom_veku": "   0",
    "Počet_mužov": "   0",
    "Počet_žien": "   0"
  }
]